haystack/__init__.py
haystack/admin.py
haystack/apps.py
haystack/constants.py
haystack/exceptions.py
haystack/fields.py
haystack/forms.py
haystack/generic_views.py
haystack/indexes.py
haystack/inputs.py
haystack/manager.py
haystack/models.py
haystack/panels.py
haystack/query.py
haystack/routers.py
haystack/signals.py
haystack/urls.py
haystack/version.py
haystack/views.py
haystack/backends/__init__.py
haystack/backends/elasticsearch2_backend.py
haystack/backends/elasticsearch5_backend.py
haystack/backends/elasticsearch7_backend.py
haystack/backends/elasticsearch_backend.py
haystack/backends/simple_backend.py
haystack/backends/solr_backend.py
haystack/backends/whoosh_backend.py
haystack/management/__init__.py
haystack/management/commands/__init__.py
haystack/management/commands/build_solr_schema.py
haystack/management/commands/clear_index.py
haystack/management/commands/haystack_info.py
haystack/management/commands/rebuild_index.py
haystack/management/commands/update_index.py
haystack/templates/panels/haystack.html
haystack/templates/search_configuration/schema.xml
haystack/templates/search_configuration/solrconfig.xml
haystack/templatetags/__init__.py
haystack/templatetags/highlight.py
haystack/templatetags/more_like_this.py
haystack/utils/__init__.py
haystack/utils/app_loading.py
haystack/utils/geo.py
haystack/utils/highlighting.py
haystack/utils/loading.py
haystack/utils/log.py
django_haystack-3.1.1.dist-info/AUTHORS
django_haystack-3.1.1.dist-info/LICENSE
django_haystack-3.1.1.dist-info/METADATA
django_haystack-3.1.1.dist-info/WHEEL
django_haystack-3.1.1.dist-info/top_level.txt
django_haystack-3.1.1.dist-info/RECORD
